{"stats":{"minecraft:mined":{"minecraft:wall_sign":1,"minecraft:granite":34,"minecraft:grass_block":63,"minecraft:spruce_leaves":5,"minecraft:kelp":3,"minecraft:redstone_ore":3,"minecraft:furnace":2,"minecraft:iron_ore":10,"minecraft:snow":6,"minecraft:andesite":58,"minecraft:cobblestone_slab":3,"minecraft:rail":1,"minecraft:stone":569,"minecraft:kelp_plant":12,"minecraft:dandelion":1,"minecraft:clay":33,"minecraft:crafting_table":5,"minecraft:poppy":2,"minecraft:chest":12,"minecraft:cobblestone":11,"minecraft:sugar_cane":25,"minecraft:diorite":4,"minecraft:wall_torch":26,"minecraft:redstone_torch":5,"minecraft:ice":1,"minecraft:spruce_log":63,"minecraft:grass":1,"minecraft:oak_log":77,"minecraft:coal_ore":151,"minecraft:gravel":7,"minecraft:dirt":37,"minecraft:oak_leaves":48,"minecraft:infested_stone":2},"minecraft:dropped":{"minecraft:crafting_table":2,"minecraft:granite":69,"minecraft:dirt":2,"minecraft:diorite":3,"minecraft:iron_pickaxe":2,"minecraft:furnace":1,"minecraft:stone_sword":1,"minecraft:stone_pickaxe":1},"minecraft:crafted":{"minecraft:brick":90,"minecraft:oak_planks":216,"minecraft:cobblestone_slab":42,"minecraft:furnace":2,"minecraft:stone":23,"minecraft:cobblestone_stairs":20,"minecraft:spruce_fence":3,"minecraft:spruce_pressure_plate":1,"minecraft:iron_axe":2,"minecraft:ladder":48,"minecraft:stone_pickaxe":3,"minecraft:chest":10,"minecraft:bricks":15,"minecraft:cooked_beef":4,"minecraft:sugar":24,"minecraft:item_frame":2,"minecraft:cooked_porkchop":6,"minecraft:crafting_table":2,"minecraft:spruce_planks":248,"minecraft:wooden_pickaxe":1,"minecraft:iron_sword":1,"minecraft:sign":9,"minecraft:stick":296,"minecraft:iron_ingot":44,"minecraft:iron_pickaxe":4,"minecraft:white_bed":2,"minecraft:redstone_torch":13,"minecraft:torch":264,"minecraft:shears":1},"minecraft:used":{"minecraft:stone_sword":19,"minecraft:iron_shovel":161,"minecraft:ladder":35,"minecraft:chest":22,"minecraft:iron_sword":17,"minecraft:cooked_chicken":2,"minecraft:torch":206,"minecraft:dirt":94,"minecraft:snowball":4,"minecraft:spruce_fence":3,"minecraft:iron_axe":188,"minecraft:item_frame":4,"minecraft:furnace":3,"minecraft:oak_sapling":25,"minecraft:cooked_beef":1,"minecraft:cobblestone_stairs":20,"minecraft:stone_pickaxe":263,"minecraft:wooden_pickaxe":36,"minecraft:cobblestone_slab":21,"minecraft:sugar_cane":10,"minecraft:rail":1,"minecraft:crafting_table":7,"minecraft:white_bed":1,"minecraft:redstone_torch":5,"minecraft:apple":3,"minecraft:iron_pickaxe":553,"minecraft:spruce_pressure_plate":1,"minecraft:sign":1,"minecraft:spruce_sapling":25,"minecraft:cobblestone":147,"minecraft:cooked_porkchop":2,"minecraft:porkchop":1,"minecraft:andesite":4},"minecraft:picked_up":{"minecraft:fishing_rod":1,"minecraft:crafting_table":8,"minecraft:wheat":5,"minecraft:black_carpet":2,"minecraft:purple_wool":7,"minecraft:clay_ball":132,"minecraft:lead":1,"minecraft:iron_axe":3,"minecraft:item_frame":2,"minecraft:iron_shovel":1,"minecraft:magenta_wool":6,"minecraft:cyan_carpet":9,"minecraft:spruce_planks":67,"minecraft:beef":4,"minecraft:cobblestone_slab":5,"minecraft:redstone_torch":5,"minecraft:cyan_wool":4,"minecraft:light_gray_wool":11,"minecraft:poppy":6,"minecraft:iron_pickaxe":1,"minecraft:spruce_slab":8,"minecraft:coal_block":19,"minecraft:sugar_cane":40,"minecraft:chest":12,"minecraft:egg":8,"minecraft:furnace":2,"minecraft:lime_wool":4,"minecraft:stick":96,"minecraft:torch":188,"minecraft:spruce_stairs":5,"minecraft:spruce_fence":3,"minecraft:porkchop":7,"minecraft:diorite":4,"minecraft:redstone":14,"minecraft:blue_carpet":15,"minecraft:stone_sword":3,"minecraft:arrow":1,"minecraft:light_blue_wool":7,"minecraft:tropical_fish":1,"minecraft:shears":1,"minecraft:rail":1,"minecraft:snowball":6,"minecraft:white_wool":25,"minecraft:cobblestone":1070,"minecraft:feather":2,"minecraft:cooked_beef":3,"minecraft:andesite":56,"minecraft:brown_wool":4,"minecraft:leather":2,"minecraft:oak_log":77,"minecraft:gunpowder":4,"minecraft:dirt":100,"minecraft:glass":69,"minecraft:sign":10,"minecraft:red_carpet":1,"minecraft:bone":3,"minecraft:apple":3,"minecraft:kelp":31,"minecraft:wheat_seeds":18,"minecraft:iron_ingot":3,"minecraft:stone_pickaxe":3,"minecraft:iron_ore":13,"minecraft:iron_sword":1,"minecraft:cooked_porkchop":4,"minecraft:dandelion":1,"minecraft:gravel":7,"minecraft:spruce_sapling":26,"minecraft:spruce_log":115,"minecraft:spruce_door":2,"minecraft:light_blue_carpet":9,"minecraft:granite":80,"minecraft:gray_wool":1,"minecraft:oak_sapling":29,"minecraft:coal":157},"minecraft:custom":{"minecraft:mob_kills":11,"minecraft:interact_with_crafting_table":36,"minecraft:leave_game":7,"minecraft:time_since_death":141909,"minecraft:climb_one_cm":19203,"minecraft:sprint_one_cm":90132,"minecraft:walk_one_cm":864736,"minecraft:drop":81,"minecraft:deaths":1,"minecraft:sneak_time":8481,"minecraft:walk_under_water_one_cm":111264,"minecraft:jump":1023,"minecraft:walk_on_water_one_cm":98834,"minecraft:interact_with_furnace":24,"minecraft:play_one_minute":247869,"minecraft:sleep_in_bed":3,"minecraft:time_since_rest":17969,"minecraft:damage_taken":857,"minecraft:trigger_trapped_chest":4,"minecraft:minecart_one_cm":10206,"minecraft:damage_dealt":1347,"minecraft:fly_one_cm":8314,"minecraft:open_chest":122,"minecraft:crouch_one_cm":16859,"minecraft:fall_one_cm":13241},"minecraft:broken":{"minecraft:stone_pickaxe":2,"minecraft:iron_pickaxe":2},"minecraft:killed":{"minecraft:silverfish":1,"minecraft:tropical_fish":1,"minecraft:pig":3,"minecraft:creeper":1,"minecraft:zombie":2,"minecraft:cow":2}},"DataVersion":1631}